advice_animal/__init__.py
advice_animal/_version.py
advice_animal/api.py
advice_animal/cli.py
advice_animal/naming.py
advice_animal/py.typed
advice_animal/runner.py
advice_animal/update_checkout.py
advice_animal/workflow.py
advice_animal-0.4.5.dist-info/licenses/LICENSE
advice_animal-0.4.5.dist-info/METADATA
advice_animal-0.4.5.dist-info/WHEEL
advice_animal-0.4.5.dist-info/entry_points.txt
advice_animal-0.4.5.dist-info/top_level.txt
advice_animal-0.4.5.dist-info/RECORD
