Metadata-Version: 2.4
Name: advice-animal
Version: 0.4.5
Summary: Suggests incremental improvements for existing projects
Home-page: https://github.com/advice-animal/advice-animal/
Author: Tim Hatch
Author-email: tim@timhatch.com
License: MIT
Requires-Python: >=3.9
License-File: LICENSE
Requires-Dist: appdirs
Requires-Dist: click
Requires-Dist: tomlkit
Requires-Dist: imperfect
Requires-Dist: moreorless
Requires-Dist: pathspec
Requires-Dist: vmodule
Requires-Dist: filelock
Provides-Extra: dev
Requires-Dist: ruff==0.8.0; extra == "dev"
Requires-Dist: checkdeps==0.9.0; extra == "dev"
Requires-Dist: pre-commit==3.7.0; extra == "dev"
Requires-Dist: mypy==1.13.0; extra == "dev"
Requires-Dist: tox==4.23.2; extra == "dev"
Provides-Extra: test
Requires-Dist: pytest; extra == "test"
Requires-Dist: coverage>=6; extra == "test"
Dynamic: license-file
